flask_healthz/__init__.py
flask_healthz/blueprint.py
flask_healthz/ext.py
flask_healthz/log.py
flask_healthz/tests/conftest.py
flask_healthz/tests/test_blueprint.py
flask_healthz/tests/test_ext.py
flask_healthz/tests/test_log.py
flask_healthz-1.0.0.dist-info/LICENSE
flask_healthz-1.0.0.dist-info/METADATA
flask_healthz-1.0.0.dist-info/WHEEL
flask_healthz-1.0.0.dist-info/RECORD
