Metadata-Version: 2.1
Name: flask-healthz
Version: 1.0.0
Summary: A simple module to allow you to easily add health endpoints to your Flask application
Home-page: https://github.com/fedora-infra/flask-healthz
License: BSD-3-Clause
Author: Fedora Infrastructure
Author-email: admin@fedoraproject.org
Requires-Python: >=3.7.0,<4.0.0
Classifier: License :: OSI Approved :: BSD License
Classifier: Programming Language :: Python :: 3
Classifier: Programming Language :: Python :: 3.7
Classifier: Programming Language :: Python :: 3.8
Classifier: Programming Language :: Python :: 3.9
Classifier: Programming Language :: Python :: 3.10
Classifier: Programming Language :: Python :: 3.11
Requires-Dist: flask (<3.0.1)
Project-URL: Repository, https://github.com/fedora-infra/flask-healthz
